{
    "year" : 2017,
    "month" : 2,
    "day" : 19,
    "hour" : 23,
    "min" : 42,
    "title" : "돔에 대해서 공부",
    "content" : "누구나 돔을 다룰줄은 안다. 하지만 제이쿼리와 같은 라이브러리가 있어 돔에 매우 둔감해지는건 사실이다. 돔을 잘 다룬다는건 자바스크립트를 잘 이해하고 있다는 생각이 든다. 아직은 잘 모르겠지만. 예전부터 나는 돔을 중시해왔고 돔에 대해서 조금씩 공부해왔지만 돔은 하면 할수록 뭔가 깊이가 느껴지는 것 같았다. 그래서 이번에 돔에 대한 관련 책도 있고하여 돔에 대해서 집중적으로 조명하며 공부할 생각을 가졌고 오늘 이렇게 돔에 대해서 파보았다. 이론 그리고 이론... 이론 끝에 이론.. 매우 지루했지만 사실 매우 지루했다. 매우 간단한 것도 그냥 넘어가지 않고 코드를 하나 하나씩 써보면서 하니 너무 지루했다. 하지만 내용은 좋았다. 그동안 잘 알지 못하고 그냥 둔감한채 넘어갔던 돔에 대한 이론적인 부분도 알게되었고 몇가지 잘 모르던 메서드들도 파악할 수 있었을 분더러 나쁘진 않은 시간이였지만 내일부터는 좀 속성으로 읽으면서 필요한 부분만 코드로 남기로 하면서 책을 넘겨볼 것이다. 생각보다 할게 많아졌다. 하고싶은 것도 많아졌고 돔에 대해 긴 시간을 투자하고싶지만 그러질 못하니 정말 알짜배기 상식들만 다 삼켜서 먹어야겠다는 생각을 오늘 하루의 경험을 통해 하게되었다. 아둔님이 주신 책인만큼 더 더욱 열심히 볼것이다.",
    "til" :[],
    "nice" : "돔에 대한 집중 공부",
    "bad" : "매우 이론에 치중해서 진도가 너무 느리게 나가게 되었다.",
    "imp" : "내일부터는 조금씩 속도내면서 속도전 알짜배기 정보들만 집어삼켜보자."
}